intervalop/__init__.py
intervalop/interval.py
intervalop-0.0.1.dist-info/METADATA
intervalop-0.0.1.dist-info/WHEEL
intervalop-0.0.1.dist-info/licenses/LICENSE
intervalop-0.0.1.dist-info/RECORD
