Metadata-Version: 2.4
Name: intervalop
Version: 0.0.1
Summary: A package for basic interval operations.
Project-URL: Homepage, https://github.com/leesugil/interval
Project-URL: Issues, https://github.com/leesugil/interval/issues
Author-email: Sugil Steve Lee <sugilmath@gmail.com>
License-Expression: GPL-3.0-or-later
License-File: LICENSE
Classifier: Operating System :: OS Independent
Classifier: Programming Language :: Python :: 3
Requires-Python: >=3.9
